AUTHORS.txt
LICENSE.txt
MANIFEST.in
README.md
pyproject.toml
setup.py
menpo/__init__.py
menpo/_static_version.py
menpo/_version.py
menpo/base.py
menpo/testing.py
menpo.egg-info/PKG-INFO
menpo.egg-info/SOURCES.txt
menpo.egg-info/dependency_links.txt
menpo.egg-info/requires.txt
menpo.egg-info/top_level.txt
menpo/data/breakingbad.jpg
menpo/data/breakingbad.pts
menpo/data/einstein.jpg
menpo/data/einstein.pts
menpo/data/lenna.ljson
menpo/data/lenna.png
menpo/data/menpo_thumbnail.jpg
menpo/data/takeo.ppm
menpo/data/takeo.pts
menpo/data/tongue.jpg
menpo/data/tongue.pts
menpo/external/__init__.py
menpo/external/skimage/__init__.py
menpo/external/skimage/_daisy.py
menpo/feature/__init__.py
menpo/feature/base.py
menpo/feature/features.py
menpo/feature/predefined.py
menpo/feature/visualize.py
menpo/feature/optional/__init__.py
menpo/feature/optional/vlfeat.py
menpo/feature/test/__init__.py
menpo/feature/test/test_features.py
menpo/feature/test/test_gradient.py
menpo/image/__init__.py
menpo/image/base.py
menpo/image/boolean.py
menpo/image/interpolation.py
menpo/image/masked.py
menpo/image/patches.py
menpo/image/rasterize.py
menpo/image/test/__init__.py
menpo/image/test/test_boolean_image_constrain.py
menpo/image/test/test_image.py
menpo/image/test/test_image_basics.py
menpo/image/test/test_image_blank.py
menpo/image/test/test_image_copy.py
menpo/image/test/test_image_gaussian.py
menpo/image/test/test_image_masked.py
menpo/image/test/test_image_patches.py
menpo/image/test/test_image_pixel_recale.py
menpo/image/test/test_image_pointcloud_rescale_crop.py
menpo/image/test/test_image_update_from_vector.py
menpo/image/test/test_image_warp.py
menpo/image/test/test_rasterize.py
menpo/io/__init__.py
menpo/io/exceptions.py
menpo/io/utils.py
menpo/io/input/__init__.py
menpo/io/input/base.py
menpo/io/input/extensions.py
menpo/io/input/image.py
menpo/io/input/landmark.py
menpo/io/input/landmark_image.py
menpo/io/input/pickle.py
menpo/io/input/video.py
menpo/io/output/__init__.py
menpo/io/output/base.py
menpo/io/output/extensions.py
menpo/io/output/image.py
menpo/io/output/landmark.py
menpo/io/output/pickle.py
